shipyard_openai_chatgpt/__init__.py
shipyard_openai_chatgpt/cli/__init__.py
shipyard_openai_chatgpt/cli/chatgpt_translation.py
shipyard_openai_chatgpt/cli/comment_code.py
shipyard_openai_chatgpt/cli/data_dictionary.py
shipyard_openai_chatgpt/cli/dummy_data.py
shipyard_openai_chatgpt/cli/generate_message.py
shipyard_openai_chatgpt/cli/generate_response.py
shipyard_openai_chatgpt/cli/gpt_meeting_notes.py
shipyard_openai_chatgpt-0.2.0.dist-info/METADATA
shipyard_openai_chatgpt-0.2.0.dist-info/WHEEL
shipyard_openai_chatgpt-0.2.0.dist-info/top_level.txt
shipyard_openai_chatgpt-0.2.0.dist-info/RECORD
